{
  "data": {
    "article": {},
    "attachments": {},
    "author_id": "1806043502771593216",
    "conversation_id": "2027120532013851077",
    "created_at": "2026-02-28T12:06:35.000Z",
    "edit_controls": {
      "editable_until": "2026-02-28T13:06:35.000Z",
      "edits_remaining": 5,
      "is_edit_eligible": false
    },
    "edit_history_tweet_ids": [
      "2027717061288571000"
    ],
    "entities": {
      "mentions": [
        {
          "end": 12,
          "id": "1095597368131506176",
          "start": 0,
          "username": "Madame1111D"
        }
      ]
    },
    "geo": {},
    "id": "2027717061288571000",
    "in_reply_to_user_id": "1095597368131506176",
    "lang": "zh",
    "note_tweet": {
      "entities": {}
    },
    "possibly_sensitive": false,
    "public_metrics": {
      "bookmark_count": 0,
      "impression_count": 0,
      "like_count": 0,
      "quote_count": 0,
      "reply_count": 0,
      "retweet_count": 0
    },
    "referenced_tweets": [
      {
        "id": "2027120532013851077",
        "type": "replied_to"
      }
    ],
    "reply_settings": "everyone",
    "text": "@Madame1111D 从姐姐骂人的帖子点进来才看见的！超级美的身材为什么会有人觉得胖。。这种力量感特别特别完美、、"
  },
  "includes": {
    "media": [
      {
        "height": 2048,
        "media_key": "3_2027120523335905280",
        "public_metrics": {},
        "type": "photo",
        "url": "https://pbs.twimg.com/media/HCHHYDZXMAAFUZe.jpg",
        "width": 1536
      }
    ],
    "tweets": [
      {
        "article": {},
        "attachments": {},
        "author_id": "1806043502771593216",
        "conversation_id": "2027120532013851077",
        "created_at": "2026-02-28T12:06:35.000Z",
        "edit_controls": {
          "editable_until": "2026-02-28T13:06:35.000Z",
          "edits_remaining": 5,
          "is_edit_eligible": false
        },
        "edit_history_tweet_ids": [
          "2027717061288571000"
        ],
        "entities": {
          "mentions": [
            {
              "end": 12,
              "id": "1095597368131506176",
              "start": 0,
              "username": "Madame1111D"
            }
          ]
        },
        "geo": {},
        "id": "2027717061288571000",
        "in_reply_to_user_id": "1095597368131506176",
        "lang": "zh",
        "note_tweet": {
          "entities": {}
        },
        "possibly_sensitive": false,
        "public_metrics": {
          "bookmark_count": 0,
          "impression_count": 0,
          "like_count": 0,
          "quote_count": 0,
          "reply_count": 0,
          "retweet_count": 0
        },
        "referenced_tweets": [
          {
            "id": "2027120532013851077",
            "type": "replied_to"
          }
        ],
        "reply_settings": "everyone",
        "text": "@Madame1111D 从姐姐骂人的帖子点进来才看见的！超级美的身材为什么会有人觉得胖。。这种力量感特别特别完美、、"
      },
      {
        "article": {},
        "attachments": {
          "media_keys": [
            "3_2027120523335905280"
          ]
        },
        "author_id": "1095597368131506176",
        "conversation_id": "2027120532013851077",
        "created_at": "2026-02-26T20:36:11.000Z",
        "edit_controls": {
          "editable_until": "2026-02-26T21:36:11.000Z",
          "edits_remaining": 5,
          "is_edit_eligible": true
        },
        "edit_history_tweet_ids": [
          "2027120532013851077"
        ],
        "entities": {
          "hashtags": [
            {
              "end": 22,
              "start": 19,
              "tag": "德国"
            },
            {
              "end": 26,
              "start": 23,
              "tag": "女s"
            },
            {
              "end": 32,
              "start": 27,
              "tag": "女dom"
            }
          ],
          "urls": [
            {
              "display_url": "pic.x.com/UTaG5FfjKy",
              "end": 56,
              "expanded_url": "https://x.com/Madame1111D/status/2027120532013851077/photo/1",
              "media_key": "3_2027120523335905280",
              "start": 33,
              "url": "https://t.co/UTaG5FfjKy"
            }
          ]
        },
        "geo": {},
        "id": "2027120532013851077",
        "lang": "zh",
        "note_tweet": {
          "entities": {}
        },
        "possibly_sensitive": false,
        "public_metrics": {
          "bookmark_count": 7,
          "impression_count": 17381,
          "like_count": 180,
          "quote_count": 0,
          "reply_count": 16,
          "retweet_count": 2
        },
        "reply_settings": "everyone",
        "text": "这个身材能找到老婆吗\n找不到我再练练\n#德国 #女s #女dom https://t.co/UTaG5FfjKy"
      }
    ],
    "users": [
      {
        "created_at": "2024-06-26T19:15:08.000Z",
        "description": "不键政，很温良，本号大部分内容为欧滴/负能/自设稿件相关，直fo/点赞就是喜欢你！如果想要聊天可以随时私信我，期待能和大家好好相处！",
        "id": "1806043502771593216",
        "name": "Just Monika aa aa a",
        "pinned_tweet_id": "2024213765366173830",
        "profile_image_url": "https://pbs.twimg.com/profile_images/2016276372227055617/A5CyiFOh_normal.jpg",
        "protected": false,
        "public_metrics": {
          "followers_count": 19,
          "following_count": 42,
          "like_count": 58,
          "listed_count": 0,
          "media_count": 5,
          "tweet_count": 108
        },
        "username": "JustMonika97899",
        "verified": false
      },
      {
        "created_at": "2019-02-13T08:15:42.000Z",
        "description": "🇩🇪dom｜人生就是要活的爽｜无照不回",
        "id": "1095597368131506176",
        "location": "Deutschland",
        "name": "Madame D",
        "profile_image_url": "https://pbs.twimg.com/profile_images/2014026935567822849/DByHGJdt_normal.jpg",
        "protected": false,
        "public_metrics": {
          "followers_count": 2925,
          "following_count": 560,
          "like_count": 63,
          "listed_count": 5,
          "media_count": 56,
          "tweet_count": 773
        },
        "username": "Madame1111D",
        "verified": false
      }
    ]
  }
}