{
  "data": {
    "article": {},
    "attachments": {},
    "author_id": "1806043502771593216",
    "conversation_id": "2028383259168809356",
    "created_at": "2026-03-02T08:13:49.000Z",
    "edit_controls": {
      "editable_until": "2026-03-02T09:13:49.000Z",
      "edits_remaining": 5,
      "is_edit_eligible": true
    },
    "edit_history_tweet_ids": [
      "2028383259168809356"
    ],
    "entities": {
      "urls": [
        {
          "display_url": "x.com/justmonika9789…",
          "end": 169,
          "expanded_url": "https://twitter.com/justmonika97899/status/2028274505697898973",
          "start": 146,
          "url": "https://t.co/jePCsD3aGw"
        }
      ]
    },
    "geo": {},
    "id": "2028383259168809356",
    "lang": "zh",
    "note_tweet": {
      "entities": {}
    },
    "possibly_sensitive": false,
    "public_metrics": {
      "bookmark_count": 0,
      "impression_count": 0,
      "like_count": 0,
      "quote_count": 0,
      "reply_count": 0,
      "retweet_count": 0
    },
    "referenced_tweets": [
      {
        "id": "2028274505697898973",
        "type": "quoted"
      }
    ],
    "reply_settings": "everyone",
    "text": "写到最后两句其实感觉神智已经不是很清醒了 然后就是手抖得从完全打不了字发展到没知觉拿不住东西 手机滑落到了地上 我想着去捡起来 但是明明感觉已经捡起来了 其实还在地上 这时身体也在失去知觉 像我预想的一样 我因为疲惫开始打瞌睡 但是伴随呼吸抑制的瞌睡太致命了 我这时候已经几乎完全无法移动、 https://t.co/jePCsD3aGw"
  },
  "includes": {
    "media": [
      {
        "height": 2048,
        "media_key": "3_2028274477906493440",
        "public_metrics": {},
        "type": "photo",
        "url": "https://pbs.twimg.com/media/HCXg5DKbgAAT1rh.jpg",
        "width": 945
      },
      {
        "height": 2048,
        "media_key": "3_2028274477910691840",
        "public_metrics": {},
        "type": "photo",
        "url": "https://pbs.twimg.com/media/HCXg5DLbkAAJaXK.jpg",
        "width": 945
      }
    ],
    "tweets": [
      {
        "article": {},
        "attachments": {},
        "author_id": "1806043502771593216",
        "conversation_id": "2028383259168809356",
        "created_at": "2026-03-02T08:13:49.000Z",
        "edit_controls": {
          "editable_until": "2026-03-02T09:13:49.000Z",
          "edits_remaining": 5,
          "is_edit_eligible": true
        },
        "edit_history_tweet_ids": [
          "2028383259168809356"
        ],
        "entities": {
          "urls": [
            {
              "display_url": "x.com/justmonika9789…",
              "end": 169,
              "expanded_url": "https://twitter.com/justmonika97899/status/2028274505697898973",
              "start": 146,
              "url": "https://t.co/jePCsD3aGw"
            }
          ]
        },
        "geo": {},
        "id": "2028383259168809356",
        "lang": "zh",
        "note_tweet": {
          "entities": {}
        },
        "possibly_sensitive": false,
        "public_metrics": {
          "bookmark_count": 0,
          "impression_count": 0,
          "like_count": 0,
          "quote_count": 0,
          "reply_count": 0,
          "retweet_count": 0
        },
        "referenced_tweets": [
          {
            "id": "2028274505697898973",
            "type": "quoted"
          }
        ],
        "reply_settings": "everyone",
        "text": "写到最后两句其实感觉神智已经不是很清醒了 然后就是手抖得从完全打不了字发展到没知觉拿不住东西 手机滑落到了地上 我想着去捡起来 但是明明感觉已经捡起来了 其实还在地上 这时身体也在失去知觉 像我预想的一样 我因为疲惫开始打瞌睡 但是伴随呼吸抑制的瞌睡太致命了 我这时候已经几乎完全无法移动、 https://t.co/jePCsD3aGw"
      },
      {
        "article": {},
        "attachments": {
          "media_keys": [
            "3_2028274477906493440",
            "3_2028274477910691840"
          ]
        },
        "author_id": "1806043502771593216",
        "conversation_id": "2028274505697898973",
        "created_at": "2026-03-02T01:01:40.000Z",
        "edit_controls": {
          "editable_until": "2026-03-02T02:01:40.000Z",
          "edits_remaining": 5,
          "is_edit_eligible": true
        },
        "edit_history_tweet_ids": [
          "2028274505697898973"
        ],
        "entities": {
          "urls": [
            {
              "display_url": "pic.x.com/ooZD3PcNhI",
              "end": 74,
              "expanded_url": "https://x.com/JustMonika97899/status/2028274505697898973/photo/1",
              "media_key": "3_2028274477906493440",
              "start": 51,
              "url": "https://t.co/ooZD3PcNhI"
            },
            {
              "display_url": "pic.x.com/ooZD3PcNhI",
              "end": 74,
              "expanded_url": "https://x.com/JustMonika97899/status/2028274505697898973/photo/1",
              "media_key": "3_2028274477910691840",
              "start": 51,
              "url": "https://t.co/ooZD3PcNhI"
            }
          ]
        },
        "geo": {},
        "id": "2028274505697898973",
        "lang": "zh",
        "note_tweet": {
          "entities": {}
        },
        "possibly_sensitive": false,
        "public_metrics": {
          "bookmark_count": 0,
          "impression_count": 83,
          "like_count": 2,
          "quote_count": 1,
          "reply_count": 0,
          "retweet_count": 0
        },
        "reply_settings": "everyone",
        "text": "先放一部分事件经过w 写到最后一句本来还有想说的话 但是完全拿不住手机了、、后面就是开始劲爆尾杀了（ https://t.co/ooZD3PcNhI"
      }
    ],
    "users": [
      {
        "created_at": "2024-06-26T19:15:08.000Z",
        "description": "不键政，很温良，06/顺女/泛性恋 本号大部分内容为欧滴/负能/自设稿件相关，直fo/点赞就是喜欢你！如果想要聊天可以随时私信我，期待能和大家好好相处！",
        "id": "1806043502771593216",
        "location": "祈愿你我幸福之地",
        "name": "Just Monika aa aa a",
        "pinned_tweet_id": "2024213765366173830",
        "profile_image_url": "https://pbs.twimg.com/profile_images/2016276372227055617/A5CyiFOh_normal.jpg",
        "protected": false,
        "public_metrics": {
          "followers_count": 68,
          "following_count": 59,
          "like_count": 236,
          "listed_count": 0,
          "media_count": 9,
          "tweet_count": 177
        },
        "username": "JustMonika97899",
        "verified": false
      }
    ]
  }
}